snowduck/__init__.py
snowduck-0.0.1.dist-info/LICENSE
snowduck-0.0.1.dist-info/METADATA
snowduck-0.0.1.dist-info/WHEEL
snowduck-0.0.1.dist-info/RECORD
